AUTHORS.rst
CONTRIBUTING.rst
HISTORY.rst
LICENSE
MANIFEST.in
README.rst
requirements_dev.txt
requirements_prod.txt
setup.cfg
setup.py
docs/Makefile
docs/authors.rst
docs/conf.py
docs/contributing.rst
docs/history.rst
docs/index.rst
docs/installation.rst
docs/make.bat
docs/readme.rst
docs/usage.rst
extension/.editorconfig
extension/bind.cc
extension/stateful_unidirectional_lstm.cc
extension/stateful_unidirectional_lstm.h
extension/unidirectional_lstm.cc
extension/unidirectional_lstm.h
pytorch_stateful_lstm/__init__.py
pytorch_stateful_lstm/unidirectional_lstm.py
pytorch_stateful_lstm.egg-info/PKG-INFO
pytorch_stateful_lstm.egg-info/SOURCES.txt
pytorch_stateful_lstm.egg-info/dependency_links.txt
pytorch_stateful_lstm.egg-info/not-zip-safe
pytorch_stateful_lstm.egg-info/requires.txt
pytorch_stateful_lstm.egg-info/top_level.txt
tests/test_stateful_unidirectional_lstm.py
tests/test_unidirectional_lstm.py