Metadata-Version: 1.1
Name: pytorch-stateful-lstm
Version: 1.6.0
Summary: None
Home-page: https://github.com/cnt-dev/pytorch-stateful-lstm
Author: Hunt Zhan
Author-email: huntzhan.dev@gmail.com
License: MIT license
Keywords: pytorch_stateful_lstm
Platform: UNKNOWN
Classifier: Development Status :: 2 - Pre-Alpha
Classifier: Intended Audience :: Developers
Classifier: License :: OSI Approved :: MIT License
Classifier: Natural Language :: English
Classifier: Programming Language :: Python :: 3
Classifier: Programming Language :: Python :: 3.6
Classifier: Programming Language :: Python :: 3.7
